lepton/particle_struct.py
lepton/group.cpython-35m-i386-linux-gnu.so
lepton/emitter.cpython-35m-i386-linux-gnu.so
lepton/renderer.cpython-35m-i386-linux-gnu.so
lepton/__init__.py
lepton/controller.py
lepton/_domain.cpython-35m-i386-linux-gnu.so
lepton/texturizer.py
lepton/system.py
lepton/domain.py
lepton/_controller.cpython-35m-i386-linux-gnu.so
lepton/_texturizer.cpython-35m-i386-linux-gnu.so
lepton/pygame_renderer.py
lepton/.libs/libGLU-9f473559.so.1.3.060501
lepton/examples/pygame_fill.py
lepton/examples/flyby.py
lepton/examples/magnet.py
lepton/examples/Particle.bmp
lepton/examples/bouncy.py
lepton/examples/flare1.png
lepton/examples/puff.png
lepton/examples/__init__.py
lepton/examples/logo.py
lepton/examples/generate.py
lepton/examples/pygame_bubble.py
lepton/examples/bubble.png
lepton/examples/splode2d.py
lepton/examples/flare5.png
lepton/examples/letters.py
lepton/examples/smoke.py
lepton/examples/tunnel.py
lepton/examples/vortex.py
lepton/examples/flare2.png
lepton/examples/splode.py
lepton/examples/fire.py
lepton/examples/flare3.png
lepton/examples/flare4.png
lepton/examples/fireworks.py
lepton/examples/logo_frames/logo2.png
lepton/examples/logo_frames/logo4.png
lepton/examples/logo_frames/logo3.png
lepton/examples/logo_frames/logo6.png
lepton/examples/logo_frames/logo5.png
lepton/examples/logo_frames/logo1.png
lepton/examples/logo_frames/logo0.png
lepton-1.0.dist-info/WHEEL
lepton-1.0.dist-info/top_level.txt
lepton-1.0.dist-info/metadata.json
lepton-1.0.dist-info/RECORD
lepton-1.0.dist-info/DESCRIPTION.rst
lepton-1.0.dist-info/METADATA
