Metadata-Version: 2.0
Name: lepton
Version: 1.0
Summary: Lepton: A high-performance, pluggable particle engine and API for Python
Home-page: https://github.com/lordmauve/lepton
Author: Daniel Pope
Author-email: mauve@mauveweb.co.uk
License: MIT
Platform: UNKNOWN
Classifier: Development Status :: 4 - Beta
Classifier: Topic :: Multimedia :: Graphics
Classifier: License :: OSI Approved :: MIT License
Classifier: Intended Audience :: Developers
Classifier: Operating System :: MacOS :: MacOS X
Classifier: Operating System :: Microsoft :: Windows
Classifier: Operating System :: POSIX
Classifier: Programming Language :: Python :: 2.7
Classifier: Programming Language :: Python :: 3.3
Classifier: Programming Language :: Python :: 3.4
